boorukits/__init__.py
boorukits/booru.py
boorukits/danbooru.py
boorukits/errors.py
boorukits/gelbooru.py
boorukits/konachan.py
boorukits/safebooru.py
boorukits-0.0.6.dist-info/LICENSE
boorukits-0.0.6.dist-info/METADATA
boorukits-0.0.6.dist-info/WHEEL
boorukits-0.0.6.dist-info/top_level.txt
boorukits-0.0.6.dist-info/RECORD
