Metadata-Version: 2.1
Name: boorukits
Version: 0.0.6
Summary: boorukits is an unofficial asynchronous library for the APIs of booru-like gallery (eg. Danbooru/Moebooru).
Home-page: https://github.com/MaikoTan/boorukits
Author: Maiko Tan
Author-email: maiko.tan.coding@gmail.com
License: MIT
Project-URL: Documentation, https://github.com/MaikoTan/boorukits
Project-URL: Source Code, https://github.com/MaikoTan/boorukits
Platform: nt
Platform: posix
Platform: os2
Classifier: Development Status :: 3 - Alpha
Classifier: Framework :: AsyncIO
Classifier: License :: OSI Approved :: MIT License
Classifier: Operating System :: MacOS
Classifier: Operating System :: Microsoft :: Windows
Classifier: Operating System :: POSIX :: Linux
Classifier: Programming Language :: Python :: 3
Classifier: Programming Language :: Python :: 3 :: Only
Classifier: Programming Language :: Python :: 3.7
Classifier: Programming Language :: Python :: 3.8
Classifier: Programming Language :: Python :: 3.9
Requires-Python: >=3.7
Requires-Dist: aiohttp (>=3.6.2)
